odoo/addons/helpdesk_mgmt_fieldservice/README.rst
odoo/addons/helpdesk_mgmt_fieldservice/__init__.py
odoo/addons/helpdesk_mgmt_fieldservice/__manifest__.py
odoo/addons/helpdesk_mgmt_fieldservice/i18n/ca.po
odoo/addons/helpdesk_mgmt_fieldservice/i18n/es.po
odoo/addons/helpdesk_mgmt_fieldservice/i18n/es_AR.po
odoo/addons/helpdesk_mgmt_fieldservice/i18n/fr.po
odoo/addons/helpdesk_mgmt_fieldservice/i18n/helpdesk_mgmt_fieldservice.pot
odoo/addons/helpdesk_mgmt_fieldservice/i18n/it.po
odoo/addons/helpdesk_mgmt_fieldservice/i18n/pt_BR.po
odoo/addons/helpdesk_mgmt_fieldservice/migrations/14.0.1.1.3/post-migrate.py
odoo/addons/helpdesk_mgmt_fieldservice/models/__init__.py
odoo/addons/helpdesk_mgmt_fieldservice/models/fsm_location.py
odoo/addons/helpdesk_mgmt_fieldservice/models/fsm_order.py
odoo/addons/helpdesk_mgmt_fieldservice/models/helpdesk_ticket.py
odoo/addons/helpdesk_mgmt_fieldservice/readme/CONFIGURE.rst
odoo/addons/helpdesk_mgmt_fieldservice/readme/CONTRIBUTORS.rst
odoo/addons/helpdesk_mgmt_fieldservice/readme/DESCRIPTION.rst
odoo/addons/helpdesk_mgmt_fieldservice/readme/HISTORY.rst
odoo/addons/helpdesk_mgmt_fieldservice/readme/INSTALL.rst
odoo/addons/helpdesk_mgmt_fieldservice/readme/ROADMAP.rst
odoo/addons/helpdesk_mgmt_fieldservice/readme/USAGE.rst
odoo/addons/helpdesk_mgmt_fieldservice/security/ir.model.access.csv
odoo/addons/helpdesk_mgmt_fieldservice/static/description/icon.png
odoo/addons/helpdesk_mgmt_fieldservice/static/description/index.html
odoo/addons/helpdesk_mgmt_fieldservice/static/src/scss/helpdesk_column.scss
odoo/addons/helpdesk_mgmt_fieldservice/tests/__init__.py
odoo/addons/helpdesk_mgmt_fieldservice/tests/test_helpdesk_ticket_fsm_order.py
odoo/addons/helpdesk_mgmt_fieldservice/views/fsm_location_views.xml
odoo/addons/helpdesk_mgmt_fieldservice/views/fsm_order_views.xml
odoo/addons/helpdesk_mgmt_fieldservice/views/helpdesk_ticket_views.xml
odoo/addons/helpdesk_mgmt_fieldservice/views/res_partner.xml
odoo14_addon_helpdesk_mgmt_fieldservice-14.0.1.1.4.dist-info/METADATA
odoo14_addon_helpdesk_mgmt_fieldservice-14.0.1.1.4.dist-info/WHEEL
odoo14_addon_helpdesk_mgmt_fieldservice-14.0.1.1.4.dist-info/top_level.txt
odoo14_addon_helpdesk_mgmt_fieldservice-14.0.1.1.4.dist-info/RECORD
