Metadata-Version: 2.1
Name: odoo14-addon-helpdesk_mgmt_fieldservice
Version: 14.0.1.1.4
Summary: Create service orders from a ticket
Home-page: https://github.com/OCA/helpdesk
Author: Open Source Integrators, Escodoo, Odoo Community Association (OCA)
Author-email: support@odoo-community.org
License: AGPL-3
Classifier: Programming Language :: Python
Classifier: Framework :: Odoo
Classifier: Framework :: Odoo :: 14.0
Classifier: License :: OSI Approved :: GNU Affero General Public License v3
Requires-Python: >=3.6
Requires-Dist: odoo14-addon-fieldservice
Requires-Dist: odoo14-addon-helpdesk-mgmt
Requires-Dist: odoo<14.1dev,>=14.0a
